Workbook

Sheet Raw Data
A1: Year | B1: Revenue | C1: Operating Income | D1: Net Income | E1: Total Assets | F1: Total Libilities
A2: 2022 | B2: 35466 | C2: =B2*20% -> 7093.2 | D2: 4967
A3: 2023 | B3: 36662 | C3: =B3*22% -> 8065.64 | D3: 5672 | E3: 61525 | F3: =E3-15856 -> 45669
A4: 2024 | B4: 38498 | C4: =B4*22% -> 8469.56 | D4: 5740 | E4: 75196 | F4: =E4-18619 -> 56577

Sheet Ratio Analysis
A1: Year | B1: Revenue Growth % | C1: Operating Margin % | D1: Net Profit Margin % | E1: Debt-to-Assets Ratio
A2: ='Raw Data'!A2 -> 2022 | C2: ='Raw Data'!C2/'Raw Data'!B2 -> 0.2 | D2: ='Raw Data'!D2/'Raw Data'!B2 -> 0.14004962
A3: ='Raw Data'!A3 -> 2023 | B3: =('Raw Data'!B3-'Raw Data'!B2)/'Raw Data'!B2 -> 0.033722438 | C3: ='Raw Data'!C3/'Raw Data'!B3 -> 0.22 | D3: ='Raw Data'!D3/'Raw Data'!B3 -> 0.1547106 | E3: ='Raw Data'!F3/'Raw Data'!E3 -> 0.74228362
A4: ='Raw Data'!A4 -> 2024 | B4: =('Raw Data'!B4-'Raw Data'!B3)/'Raw Data'!B3 -> 0.050079101 | C4: ='Raw Data'!C4/'Raw Data'!B4 -> 0.22 | D4: ='Raw Data'!D4/'Raw Data'!B4 -> 0.14909865 | E4: ='Raw Data'!F4/'Raw Data'!E4 -> 0.75239374
A37: rev growth % = Cur rev -Prev rev / Prev Rev * 100
A38: OM = OI/REV * 100
A39: Net profit marg = NI/REV *100
A40: debt to assets = TL/TA *100

Sheet Charts

Sheet Dashboard
A1: Honeywell Financial Performance Dashboard
A2: KPI | B2: Value
A3: 2024 Revenue | B3: ='Raw Data'!B4 -> 38498
A4: 2024 Net Income | B4: ='Raw Data'!D4 -> 5740
A5: 2024 Operating Margin | B5: ='Ratio Analysis'!C4 -> 0.22
A6: 2024 Debt to Assets Ratio | B6: ='Ratio Analysis'!E4 -> 0.75239374
A24: Key Insights
A25: Revenue increased steadily from 2022-2024, indicating continued business growth
A26: Operating margins improved, showing stronger operational efficiency
A27: Net Profit margins remained relatively stable despite market fluctuations
A28: Debt to assets ratios suggest Honeywell maintains moderate leverage levels

Sheet Executive Summary
A1: Honeywell Financial Performance Analysis
A3: Objective
A4: The overall objective of this project was to analyze Honeywells's financial performance from 2022-2024 using Excel-based financial analysis techniques.
A5: The analysis focused on revenue growth, profitability, operational efficiency, and financial leverage to evalute the company's overall financial health.
A7: Key Insights
A8: Revenue increased steadily from 2022-2024, indicating continued business growth
A9: Operating margins improved, showing stronger operational efficiency
A10: Net Profit margins remained relatively stable despite market fluctuations
A11: Debt to assets ratios suggest Honeywell maintains moderate leverage levels
A13: Skills
A14: Financial Statement Analysis
A15: Ratio Analysis
... A20: Executive Reporting
